{
  "$schema": "https://schema.management.azure.com/schemas/2015-01-01/deploymentTemplate.json#",
  "contentVersion": "1.0.0.0",
  "parameters": {
    "appName": {
      "type": "string"
    },
    "rootZoneName": {
      "type": "string"
    },
    "appgwPublicIpName": {
      "type": "string"
    }
  },
  "variables": {
  },
  "resources": [
    {
      "type": "Microsoft.Network/dnszones",
      "name": "[parameters('rootZoneName')]",
      "apiVersion": "2016-04-01",
      "location": "global",
      "tags": {},
      "properties": {
        "maxNumberOfRecordSets": 5000,
        "numberOfRecordSets": 3
      },
      "dependsOn": []
    }
  ],
  "outputs": {
  }
}
